bitfsd.cpython-38-x86_64-linux-gnu.so
bitfsd-0.9.14.dist-info/WHEEL
bitfsd-0.9.14.dist-info/top_level.txt
bitfsd-0.9.14.dist-info/METADATA
bitfsd-0.9.14.dist-info/RECORD
