Metadata-Version: 2.1
Name: bitfsd
Version: 0.9.14
Summary: A Formula Student Driverless Simulator using pybind11 and CMake
Home-page: https://github.com/bitfsd/vehicle-simulation
Author: Chen Tairan
Author-email: tairanchen@outlook.com
License: UNKNOWN
Platform: UNKNOWN
Provides-Extra: test
Requires-Dist: pytest ; extra == 'test'
